check_internet_speed/check_internet_speed.py
check_internet_speed-0.0.3.dist-info/LICENSE
check_internet_speed-0.0.3.dist-info/METADATA
check_internet_speed-0.0.3.dist-info/WHEEL
check_internet_speed-0.0.3.dist-info/top_level.txt
check_internet_speed-0.0.3.dist-info/RECORD
